govesb/__init__.py
govesb/v1/__init__.py
govesb/v1/esb.py
govesb/v1/govesb.py
govesb/v1/crypto/__init__.py
govesb/v1/crypto/ecc.py
govesb/v1/crypto/rsa.py
govesb/v1/models/__init__.py
govesb/v1/models/data.py
govesb/v1/models/enums.py
govesb/v1/services/__init__.py
govesb/v1/services/crypto_config.py
govesb/v1/services/esb_helper.py
govesb/v1/services/esb_helper2.py
govesb/v1/services/token_service.py
govesb/v1/utils/__init__.py
govesb/v1/utils/json_fixer.py
govesb/v2/__init__.py
govesb/v2/esb_v2.py
govesb-2.1.0.dist-info/LICENSE
govesb-2.1.0.dist-info/METADATA
govesb-2.1.0.dist-info/WHEEL
govesb-2.1.0.dist-info/top_level.txt
govesb-2.1.0.dist-info/RECORD
