Metadata-Version: 2.1
Name: govesb
Version: 2.1.0
Summary: A Python library for supporting GovESB (Government Enterprise Service Bus) Integration
Home-page: https://github.com/LarryMatrix/govesb
Author: Lawrance Massanja
Author-email: massanjal4@gmail.com
License: BSD 3-Clause License
Project-URL: Bug Reports, https://github.com/LarryMatrix/govesb/issues
Project-URL: Source, https://github.com/LarryMatrix/govesb
Keywords: govesb esb enterprise-service-bus government integration cryptography rsa ecc
Classifier: Development Status :: 4 - Beta
Classifier: Intended Audience :: Developers
Classifier: Topic :: Software Development :: Libraries :: Python Modules
Classifier: Topic :: Security :: Cryptography
Classifier: License :: OSI Approved :: BSD License
Classifier: Programming Language :: Python :: 3
Classifier: Programming Language :: Python :: 3.7
Classifier: Programming Language :: Python :: 3.8
Classifier: Programming Language :: Python :: 3.9
Classifier: Programming Language :: Python :: 3.10
Classifier: Programming Language :: Python :: 3.11
Classifier: Programming Language :: Python :: 3.12
Classifier: Operating System :: OS Independent
Requires-Python: >=3.7
License-File: LICENSE
Requires-Dist: cryptography>=44.0.0
Requires-Dist: requests>=2.32.0
Requires-Dist: xmltodict>=0.14.0
